booking_sites_parser/__init__.py
booking_sites_parser/__main__.py
booking_sites_parser/http_client.py
booking_sites_parser/models.py
booking_sites_parser/parser.py
booking_sites_parser/sources/__init__.py
booking_sites_parser/sources/airbnb.py
booking_sites_parser/sources/airbnb_mixin.py
booking_sites_parser/sources/airbnb_plus.py
booking_sites_parser-0.0.3.dist-info/METADATA
booking_sites_parser-0.0.3.dist-info/WHEEL
booking_sites_parser-0.0.3.dist-info/entry_points.txt
booking_sites_parser-0.0.3.dist-info/top_level.txt
booking_sites_parser-0.0.3.dist-info/RECORD
