Metadata-Version: 2.1
Name: booking-sites-parser
Version: 0.0.3
Summary: Parser for booking sites such as Booking.com, Homeaway.com, Airbnb.com
Home-page: https://github.com/webmalc/booking-sites-parser
Author: webmalc
Author-email: m@webmalc.pw
License: MIT
Platform: UNKNOWN
Classifier: License :: OSI Approved :: MIT License
Classifier: Programming Language :: Python :: 3
Classifier: Programming Language :: Python :: 3.6
Classifier: Programming Language :: Python :: 3.7
Requires-Python: >=3.6.0
Requires-Dist: requests
Requires-Dist: beautifulsoup4
Requires-Dist: fake-useragent
